__init__.py
pyrc_python_utils/__init__.py
pyrc_python_utils/util_datetime.py
pyrc_python_utils/util_exchange.py
pyrc_python_utils/util_file.py
pyrc_python_utils/util_ms_teams.py
pyrc_python_utils/util_s3.py
pyrc_python_utils/util_sftp.py
pyrc_python_utils/util_sharepoint.py
pyrc_python_utils/util_string.py
pyrc_python_utils-0.0.4.dist-info/LICENSE
pyrc_python_utils-0.0.4.dist-info/METADATA
pyrc_python_utils-0.0.4.dist-info/WHEEL
pyrc_python_utils-0.0.4.dist-info/top_level.txt
pyrc_python_utils-0.0.4.dist-info/RECORD
